LICENSE.txt
MANIFEST.in
README
setup.cfg
setup.py
tests.txt
zxcvbn/__init__.py
zxcvbn/main.py
zxcvbn/matching.py
zxcvbn/scoring.py
zxcvbn/generated/adjacency_graphs.json
zxcvbn/generated/frequency_lists.json
zxcvbn_dutch.egg-info/PKG-INFO
zxcvbn_dutch.egg-info/SOURCES.txt
zxcvbn_dutch.egg-info/dependency_links.txt
zxcvbn_dutch.egg-info/top_level.txt