Metadata-Version: 1.1
Name: zxcvbn-dutch
Version: 1.1
Summary: Password strength estimator with Dutch support
Home-page: https://www.github.com/erikr/python-zxcvbn
Author: Erik Romijn
Author-email: github@erik.io
License: UNKNOWN
Platform: UNKNOWN
Classifier: Intended Audience :: Developers
Classifier: Programming Language :: Python :: 2
Classifier: Programming Language :: Python :: 2.6
Classifier: Programming Language :: Python :: 2.7
Classifier: Programming Language :: Python :: 3
Classifier: Programming Language :: Python :: 3.2
Classifier: Programming Language :: Python :: 3.3
Classifier: Programming Language :: Python :: 3.4
